{"NXdThXmKApFebVWW0+OqBA==":"server-icon-64x64.png","2/w/DHkVEgH/uGEtIJsUfQ==":"logo2.png","3MLcxpktirio0xZe27W3VQ==":"mbr-244x427.png","BnjWR0UXS7RtAMbGkw44yA==":"mbr-1-244x427.png","nRvpwp3cPxSHo2K5fOBY8A==":"mbr-2-244x427.png","Y88pAF33KazPr9ezGLsx7Q==":"pmp-124x124.png","+SouOWOJpA6+hJhpAdeerw==":"mbr-1920x1080.jpg","ReG7zo9NHIi9xVqZOY66HA==":"a_e349efd9b2e100eb5b71c9c775e8397f.gif","oJN6utzY6wBje3b/Vrv7kA==":"b858ae18b98ff00b4aaa1ea696d79b2e-288x288.png","0tPlHt91JXisUHWSyU10lw==":"e217b9ee52f59a75486160bb429d8df4-256x256.png"}